{
  "batchClaimRegisteredWithDepositWithWitness": "146969",
  "batchDepositAndRegisterWithWitnessViaPermit2": "220256",
  "claim": "87704",
  "claimAndWithdraw": "116245",
  "depositAndRegisterViaPermit2": "123428",
  "depositBatchSingleERC20": "66752",
  "depositBatchSingleNative": "27039",
  "depositBatchViaPermit2NativeAndERC20": "128766",
  "depositBatchViaPermit2SingleERC20": "103893",
  "depositERC20AndURI": "66462",
  "depositERC20Basic": "66422",
  "depositERC20ViaPermit2AndURI": "98339",
  "depositETHAndURI": "26116",
  "depositETHBasic": "26587",
  "depositRegisterFor": "78791",
  "exogenousSplitBatchMultichainClaimWithWitness": "121711",
  "exogenousSplitMultichainClaimWithWitness": "92735",
  "qualified_basicTransfer": "60798",
  "register": "24473",
  "splitBatchClaimWithWitness": "146963",
  "splitBatchMultichainClaimWithWitness": "93672",
  "splitBatchTransfer": "118789",
  "splitBatchWithdrawal": "147702",
  "splitClaimWithWitness": "90658",
  "splitMultichainClaimWithWitness": "91474",
  "splitTransfer": "88011",
  "splitWithdrawal": "97081"
}